Metadata-Version: 1.1
Name: hallie
Version: 0.1.0
Summary: Like Siri, for the command line.. Forgot a command? Tell Hallie and she'll try to help. Inspired by betty.
Home-page: https://github.com/mikemelch/hallie
Author: Michael Melchione
Author-email: michaelmelchione@gmail.com
License: BSD
Keywords: hallie
Platform: UNKNOWN
Classifier: Development Status :: 2 - Pre-Alpha
Classifier: Intended Audience :: Developers
Classifier: License :: OSI Approved :: BSD License
Classifier: Natural Language :: English
Classifier: Programming Language :: Python :: 2
Classifier: Programming Language :: Python :: 2.6
Classifier: Programming Language :: Python :: 2.7
Classifier: Programming Language :: Python :: 3
Classifier: Programming Language :: Python :: 3.3
Classifier: Programming Language :: Python :: 3.4
